modkr/__init__.py
modkr/__main__.py
modkr/adb_handler.py
modkr/config_manager.py
modkr/csv_handler.py
modkr/feature_handler.py
modkr/game_data_getter.py
modkr/helper.py
modkr/item.py
modkr/locale_handler.py
modkr/managed_item.py
modkr/parse_save.py
modkr/patcher.py
modkr/root_handler.py
modkr/serialise_save.py
modkr/server_handler.py
modkr/tracker.py
modkr/updater.py
modkr/user_info.py
modkr/user_input_handler.py
modkr/edits/__init__.py
modkr/edits/basic/__init__.py
modkr/edits/basic/basic_items.py
modkr/edits/basic/catfruit.py
modkr/edits/basic/catseyes.py
modkr/edits/basic/ototo_base_mats.py
modkr/edits/basic/talent_orbs.py
modkr/edits/basic/talent_orbs_new.py
modkr/edits/cats/__init__.py
modkr/edits/cats/cat_helper.py
modkr/edits/cats/cat_id_selector.py
modkr/edits/cats/chara_drop.py
modkr/edits/cats/clear_cat_guide.py
modkr/edits/cats/evolve_cats.py
modkr/edits/cats/get_remove_cats.py
modkr/edits/cats/talents.py
modkr/edits/cats/upgrade_blue.py
modkr/edits/cats/upgrade_cats.py
modkr/edits/gamototo/__init__.py
modkr/edits/gamototo/fix_gamatoto.py
modkr/edits/gamototo/gamatoto_xp.py
modkr/edits/gamototo/helpers.py
modkr/edits/gamototo/ototo_cat_cannon.py
modkr/edits/levels/__init__.py
modkr/edits/levels/aku.py
modkr/edits/levels/allow_filibuster_clearing.py
modkr/edits/levels/behemoth_culling.py
modkr/edits/levels/clear_tutorial.py
modkr/edits/levels/enigma_stages.py
modkr/edits/levels/event_stages.py
modkr/edits/levels/gauntlet.py
modkr/edits/levels/itf_timed_scores.py
modkr/edits/levels/legend_quest.py
modkr/edits/levels/main_story.py
modkr/edits/levels/outbreaks.py
modkr/edits/levels/story_level_id_selector.py
modkr/edits/levels/towers.py
modkr/edits/levels/treasures.py
modkr/edits/levels/uncanny.py
modkr/edits/levels/unlock_aku_realm.py
modkr/edits/other/__init__.py
modkr/edits/other/cat_shrine.py
modkr/edits/other/claim_user_rank_rewards.py
modkr/edits/other/create_new_account.py
modkr/edits/other/fix_elsewhere.py
modkr/edits/other/fix_time_issues.py
Korean_editor-1.2.5.2.dist-info/METADATA
Korean_editor-1.2.5.2.dist-info/WHEEL
Korean_editor-1.2.5.2.dist-info/top_level.txt
Korean_editor-1.2.5.2.dist-info/RECORD
