Metadata-Version: 2.1
Name: Korean-editor
Version: 1.2.5.2
Summary: 냥코에디터 한글화
Home-page: https://github.com/sharkwodm/koreditor
Author: 익명
Author-email: 
License: MIT
Keywords: python,template
Classifier: Development Status :: 4 - Beta
Classifier: Intended Audience :: Developers
Classifier: License :: OSI Approved :: MIT License
Classifier: Operating System :: OS Independent
Classifier: Programming Language :: Python :: 3
Requires-Python: >=3
